AUTHORS.rst
CHANGELOG.rst
LICENSE.txt
MANIFEST.in
README.rst
setup.cfg
setup.py
aux/cadishi.bash
aux/json2yaml.py
aux/md_to_cadishi.py
aux/yaml2json.py
cadishi/__init__.py
cadishi/base.py
cadishi/dict_util.py
cadishi/dictfs.py
cadishi/githash.py
cadishi/h5pickle.py
cadishi/pbc.py
cadishi/util.py
cadishi/version.py
cadishi/worker.py
cadishi.egg-info/PKG-INFO
cadishi.egg-info/SOURCES.txt
cadishi.egg-info/dependency_links.txt
cadishi.egg-info/entry_points.txt
cadishi.egg-info/not-zip-safe
cadishi.egg-info/requires.txt
cadishi.egg-info/top_level.txt
cadishi/data/histograms_template.yaml
cadishi/exe/__init__.py
cadishi/exe/check_parameter_file.py
cadishi/exe/cli.py
cadishi/exe/histograms.py
cadishi/exe/histograms_example.py
cadishi/exe/histograms_legacy.py
cadishi/exe/merge.py
cadishi/exe/random_trajectory.py
cadishi/exe/unpack.py
cadishi/io/__init__.py
cadishi/io/ascii.py
cadishi/io/dummy.py
cadishi/io/hdf5.py
cadishi/io/md.py
cadishi/io/pickel.py
cadishi/kernel/Makefile
cadishi/kernel/README
cadishi/kernel/__init__.py
cadishi/kernel/c_cudh.pyx
cadishi/kernel/c_cudh_functions.cu
cadishi/kernel/c_dist.pyx
cadishi/kernel/c_pydh.pyx
cadishi/kernel/c_pydh_functions.cc
cadishi/kernel/common.py
cadishi/kernel/cudh.py
cadishi/kernel/dist.py
cadishi/kernel/pydh.py
cadishi/kernel/unit_tests.cc
cadishi/kernel/include/c_cudh.h
cadishi/kernel/include/c_pydh.h
cadishi/kernel/include/common.h
cadishi/kernel/include/common.hpp
cadishi/kernel/include/config.h
cadishi/kernel/include/config.hpp
cadishi/kernel/include/cuda_exceptions.hpp
cadishi/kernel/include/cudh.h
cadishi/kernel/include/exceptions.hpp
cadishi/kernel/include/pydh.h
cadishi/tests/__init__.py
cadishi/tests/minimal_driver.py
cadishi/tests/perf_kernel.py
cadishi/tests/run_tests.sh
cadishi/tests/test_base_container.py
cadishi/tests/test_dict_util.py
cadishi/tests/test_dictfs.py
cadishi/tests/test_h5pickle.py
cadishi/tests/test_pydh_cudh.py
cadishi/tests/test_pydh_dist.py
cadishi/tests/test_util_generate_random.py
cadishi/tests/data/trajectory.h5
doc/Makefile
doc/README
doc/conf.py
doc/executables.rst
doc/index.rst
doc/kernel.rst
doc/modules.rst
doc/_static/__empty__
doc/_templates/__empty__
doc/html/.buildinfo
doc/html/executables.html
