Metadata-Version: 1.0
Name: cadishi
Version: 1.1.0
Summary: High performance distance histogram calculation framework for CPUs and GPUs
Home-page: https://gitlab.mpcdf.mpg.de/MPIBP-Hummer/Cadishi
Author: Juergen Koefinger, Max Linke, Klaus Reuter
Author-email: khr@mpcdf.mpg.de
License: UNKNOWN
Platform: UNKNOWN
